shiftevent/__init__.py
shiftevent/db.py
shiftevent/db_tables.py
shiftevent/default_handlers.py
shiftevent/event.py
shiftevent/event_service.py
shiftevent/exceptions.py
shiftevent/handlers/__init__.py
shiftevent/handlers/base.py
shiftevent/handlers/dummy1.py
shiftevent/handlers/dummy2.py
shiftevent/handlers/dummy3.py
shiftevent/handlers/dummy4.py
shiftevent/handlers/no_types.py
shiftevent-0.0.15.dist-info/LICENSE.txt
shiftevent-0.0.15.dist-info/METADATA
shiftevent-0.0.15.dist-info/WHEEL
shiftevent-0.0.15.dist-info/top_level.txt
shiftevent-0.0.15.dist-info/RECORD
