Metadata-Version: 2.1
Name: shiftevent
Version: 0.0.15
Summary: Simple event store for event-sourced systems
Home-page: https://github.com/projectshift/shift-event
Author: Dmitry Belyakov
Author-email: dmitrybelyakov@gmail.com
License: MIT License
Download-URL: https://github.com/projectshift/shift-event/archive/0.0.15.tar.gz
Keywords: python3,event sourcing
Platform: UNKNOWN
Classifier: Development Status :: 3 - Alpha
Classifier: License :: OSI Approved :: MIT License
Classifier: Intended Audience :: Developers
Classifier: Intended Audience :: Information Technology
Classifier: Programming Language :: Python :: 3
Classifier: Topic :: Utilities
Classifier: Topic :: Software Development :: Libraries
Requires-Dist: shiftschema (<0.3.0,>=0.2.0)
Requires-Dist: SQLAlchemy (<1.4.0,>=1.3.1)
